LICENSE
README.md
setup.py
push_tools/__init__.py
push_tools/err.py
push_tools/push.py
push_tools/pushplus.py
push_tools/qmsg.py
push_tools/server.py
push_tools/wechat.py
push_tools.egg-info/PKG-INFO
push_tools.egg-info/SOURCES.txt
push_tools.egg-info/dependency_links.txt
push_tools.egg-info/requires.txt
push_tools.egg-info/top_level.txt