Metadata-Version: 2.1
Name: push-tools
Version: 0.0.1
Summary: A tool supports push message.
Home-page: https://github.com/arcturus-script/push-tools
Author: ARCTURUS
Author-email: ice99125@qq.com
License: MIT Licence
Keywords: qmsg,pushplus,server,wechat
Platform: any
License-File: LICENSE
Requires-Dist: requests
